smiffer/__init__.py
smiffer/__main__.py
smiffer/grid/__init__.py
smiffer/grid/class_grid.py
smiffer/grid/class_grid_factory.py
smiffer/grid/class_stamp.py
smiffer/grid/grid.py
smiffer/grid/kernel/__init__.py
smiffer/grid/kernel/class_bivariate_gaussian.py
smiffer/grid/kernel/class_gaussian.py
smiffer/grid/kernel/class_kernel.py
smiffer/grid/kernel/class_occupancy.py
smiffer/grid/property_strategy/__init__.py
smiffer/grid/property_strategy/class_apbs.py
smiffer/grid/property_strategy/class_h_bond.py
smiffer/grid/property_strategy/class_hydrophobicity.py
smiffer/grid/property_strategy/class_pi_stacking.py
smiffer/grid/property_strategy/class_property.py
smiffer/grid/trimming_strategy/__init__.py
smiffer/grid/trimming_strategy/class_occupancy.py
smiffer/grid/trimming_strategy/class_rnds.py
smiffer/grid/trimming_strategy/class_sphere.py
smiffer/grid/trimming_strategy/class_trimming.py
smiffer/parse_yaml/__init__.py
smiffer/parse_yaml/class_parse_yaml.py
smiffer/parse_yaml/class_set_parameter.py
smiffer/parse_yaml/parse_yaml.py
smiffer/utils/__init__.py
smiffer/utils/class_atom_constant.py
smiffer/utils/class_write_json.py
smiffer/utils/hbond_triplet.py
smiffer/utils/parse_argument.py
smiffer-0.3.0.dist-info/licenses/LICENSE
smiffer-0.3.0.dist-info/METADATA
smiffer-0.3.0.dist-info/WHEEL
smiffer-0.3.0.dist-info/entry_points.txt
smiffer-0.3.0.dist-info/top_level.txt
smiffer-0.3.0.dist-info/RECORD
