Metadata-Version: 2.4
Name: smiffer
Version: 0.3.0
Summary: Compute possible interaction with fields arround protein or RNA.
Author-email: Diego BARQUERO MORERA <diegobarqueromorera@gmail.com>, Lucas ROUAUD <lucas.rouaud@gmail.com>
Maintainer-email: Lucas ROUAUD <lucas.rouaud@gmail.com>
License: MIT License
Project-URL: Homepage, https://gitlab.galaxy.ibpc.fr/rouaud/smiffer
Project-URL: Documentation, https://smiffer.mol3d.tech
Project-URL: Repository, https://gitlab.galaxy.ibpc.fr/rouaud/smiffer
Keywords: python,chemical,grid,RNA,protein,properties,physical based computation,bioinformatic,chemoinformatic
Classifier: License :: OSI Approved :: MIT License
Classifier: Development Status :: 4 - Beta
Classifier: Natural Language :: English
Classifier: Programming Language :: Python :: 3.11
Classifier: Topic :: Scientific/Engineering :: Bio-Informatics
Classifier: Topic :: Scientific/Engineering :: Chemistry
Classifier: Topic :: Scientific/Engineering :: Visualization
Requires-Python: >=3.5
License-File: LICENSE
Requires-Dist: mdanalysis
Requires-Dist: numpy
Requires-Dist: pyyaml
Requires-Dist: scipy
Requires-Dist: tqdm
Provides-Extra: dev
Requires-Dist: ipython; extra == "dev"
Requires-Dist: markdown; extra == "dev"
Requires-Dist: mkdocs; extra == "dev"
Requires-Dist: mkdocs-autorefs; extra == "dev"
Requires-Dist: mkdocs-callouts; extra == "dev"
Requires-Dist: mkdocs-material; extra == "dev"
Requires-Dist: mkdocs-material-extensions; extra == "dev"
Requires-Dist: mkdocstrings; extra == "dev"
Requires-Dist: mkdocstrings-python; extra == "dev"
Requires-Dist: pylint; extra == "dev"
Requires-Dist: pymdown-extensions; extra == "dev"
Requires-Dist: pytest; extra == "dev"
Dynamic: license-file
